{"SELF-NORMAL-ANY":{"equip":"SELF-NORMAL-ANY","adv":"Cecile","ele":"wind","wt":"gun","variant":"DODGE","drg":"Gala_Beast_Volk","wep":"gun-wind-agito","wps":["A_Man_Unchanging","Memory_of_a_Friend","Sweet_Surprise","Enter_the_Blue_Rose","The_Warrioresses","Applelicious_Dreams","Testament_of_Eternity"],"coabs":["Dragonyule_Xainfried","Gala_Notte","Mona"],"share":["Weapon","Dragonyule_Lily"],"cond":"20 stormlash res & 85 poison res & 100 stun res & always connect hits & hit15","comment":"enable a1/a3 dodge every 15 seconds","real":180.13,"dps":104653,"team":0.49617504278275604,"slices":[["fs",10197],["fs_manachew",22037],["s1_manachew",18429],["s1_manachew_stormlash",3204],["s2_manachew",10539],["s2_manachew_poison",1080],["echo",4897],["dx",16094],["ds1_phase2",10333],["dmoon",1518],["dfs",6319]],"stats":{"poison":"32.6%","stormlash":"88.4%","team_att_amp":"every 29.02s from 50.07s","echo":"8099.66 avg overdamage att"}},"SELF-NORMAL-MONO":{"equip":"SELF-NORMAL-ANY","adv":"Cecile","ele":"wind","wt":"gun","variant":"DODGE","drg":"Gala_Beast_Volk","wep":"gun-wind-agito","wps":["A_Man_Unchanging","Memory_of_a_Friend","Sweet_Surprise","Enter_the_Blue_Rose","The_Warrioresses","Applelicious_Dreams","Testament_of_Eternity"],"coabs":["Dragonyule_Xainfried","Gala_Notte","Mona"],"share":["Weapon","Dragonyule_Lily"],"cond":"20 stormlash res & 85 poison res & 100 stun res & always connect hits & hit15","comment":"enable a1/a3 dodge every 15 seconds","real":180.13,"dps":104653,"team":0.49617504278275604,"slices":[["fs",10197],["fs_manachew",22037],["s1_manachew",18429],["s1_manachew_stormlash",3204],["s2_manachew",10539],["s2_manachew_poison",1080],["echo",4897],["dx",16094],["ds1_phase2",10333],["dmoon",1518],["dfs",6319]],"stats":{"poison":"32.6%","stormlash":"88.4%","team_att_amp":"every 29.02s from 50.07s","echo":"8099.66 avg overdamage att"}},"ALWAYS-NORMAL-ANY":{"equip":"ALWAYS-NORMAL-ANY","adv":"Cecile","ele":"wind","wt":"gun","variant":"DODGE","drg":"Gala_Beast_Volk","wep":"gun-wind-agito","wps":["Memory_of_a_Friend","Sweet_Surprise","The_Lurker_in_the_Woods","A_Small_Courage","The_Plaguebringer","Applelicious_Dreams","Savage_Hawk_Lance"],"coabs":["Dragonyule_Xainfried","Gala_Notte","Mona"],"share":["Weapon","Dragonyule_Lily"],"cond":"20 stormlash res & 85 poison res & 100 stun res & always connect hits & hit15","comment":"enable a1/a3 dodge every 15 seconds","real":180.06,"dps":111703,"team":0.28484400207053806,"slices":[["fs",14023],["fs_manachew",29883],["s1_manachew",22701],["s1_manachew_stormlash",3599],["s2_manachew",12617],["s2_manachew_poison",1135],["echo",2531],["dx",11929],["ds1_phase2",7592],["dmoon",1092],["dfs",4597]],"stats":{"poison":"100.0%","stormlash":"100.0%","team_att_amp":"every 28.69s from 50.57s","echo":"7419.29 avg overdamage att"}},"ALWAYS-NORMAL-MONO":{"equip":"ALWAYS-NORMAL-ANY","adv":"Cecile","ele":"wind","wt":"gun","variant":"DODGE","drg":"Gala_Beast_Volk","wep":"gun-wind-agito","wps":["Memory_of_a_Friend","Sweet_Surprise","The_Lurker_in_the_Woods","A_Small_Courage","The_Plaguebringer","Applelicious_Dreams","Savage_Hawk_Lance"],"coabs":["Dragonyule_Xainfried","Gala_Notte","Mona"],"share":["Weapon","Dragonyule_Lily"],"cond":"20 stormlash res & 85 poison res & 100 stun res & always connect hits & hit15","comment":"enable a1/a3 dodge every 15 seconds","real":180.06,"dps":111703,"team":0.28484400207053806,"slices":[["fs",14023],["fs_manachew",29883],["s1_manachew",22701],["s1_manachew_stormlash",3599],["s2_manachew",12617],["s2_manachew_poison",1135],["echo",2531],["dx",11929],["ds1_phase2",7592],["dmoon",1092],["dfs",4597]],"stats":{"poison":"100.0%","stormlash":"100.0%","team_att_amp":"every 28.69s from 50.57s","echo":"7419.29 avg overdamage att"}},"IMMUNE-NORMAL-ANY":{"equip":"IMMUNE-NORMAL-ANY","adv":"Cecile","ele":"wind","wt":"gun","variant":"DODGE","drg":"Gala_Beast_Volk","wep":"gun-wind-agito","wps":["Memory_of_a_Friend","Sweet_Surprise","The_Lurker_in_the_Woods","A_Small_Courage","The_Plaguebringer","Applelicious_Dreams","Savage_Hawk_Lance"],"coabs":["Dragonyule_Xainfried","Gala_Notte","Mona"],"share":["Weapon","Dragonyule_Lily"],"cond":"999 all affliction res & always connect hits & hit15","comment":"enable a1/a3 dodge every 15 seconds","real":180.06,"dps":60033,"team":0.28484400207053806,"slices":[["fs",7790],["fs_manachew",16601],["s1_manachew",12611],["s1_manachew_stormlash",0],["s2_manachew",7009],["s2_manachew_poison",0],["echo",2531],["dx",6109],["ds1_phase2",4217],["dmoon",606],["dfs",2554]],"stats":{"team_att_amp":"every 28.69s from 50.57s","echo":"7419.29 avg overdamage att"}},"IMMUNE-NORMAL-MONO":{"equip":"IMMUNE-NORMAL-ANY","adv":"Cecile","ele":"wind","wt":"gun","variant":"DODGE","drg":"Gala_Beast_Volk","wep":"gun-wind-agito","wps":["Memory_of_a_Friend","Sweet_Surprise","The_Lurker_in_the_Woods","A_Small_Courage","The_Plaguebringer","Applelicious_Dreams","Savage_Hawk_Lance"],"coabs":["Dragonyule_Xainfried","Gala_Notte","Mona"],"share":["Weapon","Dragonyule_Lily"],"cond":"999 all affliction res & always connect hits & hit15","comment":"enable a1/a3 dodge every 15 seconds","real":180.06,"dps":60033,"team":0.28484400207053806,"slices":[["fs",7790],["fs_manachew",16601],["s1_manachew",12611],["s1_manachew_stormlash",0],["s2_manachew",7009],["s2_manachew_poison",0],["echo",2531],["dx",6109],["ds1_phase2",4217],["dmoon",606],["dfs",2554]],"stats":{"team_att_amp":"every 28.69s from 50.57s","echo":"7419.29 avg overdamage att"}},"SELF-NIHILISM-ANY":{"equip":"SELF-NIHILISM-ANY","adv":"Cecile","ele":"wind","wt":"gun","variant":"DODGE","drg":"Gala_Beast_Volk","wep":"gun-wind-agito","wps":["Memory_of_a_Friend","Sweet_Surprise","The_Lurker_in_the_Woods","Enter_the_Blue_Rose","The_Plaguebringer","Applelicious_Dreams","Testament_of_Eternity"],"coabs":["Gala_Notte","Mona","Yukata_Lathna"],"share":["Grimnir","Formal_Joachim"],"cond":"Curse of Nihility & 0 stormlash res & 0 poison res & 100 stun res & always connect hits & hit15","comment":"enable a1/a3 dodge every 15 seconds","real":180.41,"dps":94663,"team":0.2944773191832531,"slices":[["fs",9542],["fs_manachew",21025],["s1_manachew",15610],["s1_manachew_stormlash",2232],["s2_manachew",10111],["s2_manachew_poison",2910],["s3",5631],["s4",8198],["s4_poison",3305],["s4_stormlash",1705],["dx",4748],["ds1_phase2",6901],["dmoon",871],["dfs",1867]],"stats":{"poison":"90.3%","stormlash":"89.0%","team_att_amp":"every 27.52s from 48.93s"}},"SELF-NIHILISM-MONO":{"equip":"SELF-NIHILISM-ANY","adv":"Cecile","ele":"wind","wt":"gun","variant":"DODGE","drg":"Gala_Beast_Volk","wep":"gun-wind-agito","wps":["Memory_of_a_Friend","Sweet_Surprise","The_Lurker_in_the_Woods","Enter_the_Blue_Rose","The_Plaguebringer","Applelicious_Dreams","Testament_of_Eternity"],"coabs":["Gala_Notte","Mona","Yukata_Lathna"],"share":["Grimnir","Formal_Joachim"],"cond":"Curse of Nihility & 0 stormlash res & 0 poison res & 100 stun res & always connect hits & hit15","comment":"enable a1/a3 dodge every 15 seconds","real":180.41,"dps":94663,"team":0.2944773191832531,"slices":[["fs",9542],["fs_manachew",21025],["s1_manachew",15610],["s1_manachew_stormlash",2232],["s2_manachew",10111],["s2_manachew_poison",2910],["s3",5631],["s4",8198],["s4_poison",3305],["s4_stormlash",1705],["dx",4748],["ds1_phase2",6901],["dmoon",871],["dfs",1867]],"stats":{"poison":"90.3%","stormlash":"89.0%","team_att_amp":"every 27.52s from 48.93s"}},"ALWAYS-NIHILISM-ANY":{"equip":"SELF-NIHILISM-ANY","adv":"Cecile","ele":"wind","wt":"gun","variant":"DODGE","drg":"Gala_Beast_Volk","wep":"gun-wind-agito","wps":["Memory_of_a_Friend","Sweet_Surprise","The_Lurker_in_the_Woods","Enter_the_Blue_Rose","The_Plaguebringer","Applelicious_Dreams","Testament_of_Eternity"],"coabs":["Gala_Notte","Mona","Yukata_Lathna"],"share":["Grimnir","Formal_Joachim"],"cond":"Curse of Nihility & 0 stormlash res & 0 poison res & 100 stun res & always connect hits & hit15","comment":"enable a1/a3 dodge every 15 seconds","real":180.41,"dps":94663,"team":0.2944773191832531,"slices":[["fs",9542],["fs_manachew",21025],["s1_manachew",15610],["s1_manachew_stormlash",2232],["s2_manachew",10111],["s2_manachew_poison",2910],["s3",5631],["s4",8198],["s4_poison",3305],["s4_stormlash",1705],["dx",4748],["ds1_phase2",6901],["dmoon",871],["dfs",1867]],"stats":{"poison":"90.3%","stormlash":"89.0%","team_att_amp":"every 27.52s from 48.93s"}},"ALWAYS-NIHILISM-MONO":{"equip":"SELF-NIHILISM-ANY","adv":"Cecile","ele":"wind","wt":"gun","variant":"DODGE","drg":"Gala_Beast_Volk","wep":"gun-wind-agito","wps":["Memory_of_a_Friend","Sweet_Surprise","The_Lurker_in_the_Woods","Enter_the_Blue_Rose","The_Plaguebringer","Applelicious_Dreams","Testament_of_Eternity"],"coabs":["Gala_Notte","Mona","Yukata_Lathna"],"share":["Grimnir","Formal_Joachim"],"cond":"Curse of Nihility & 0 stormlash res & 0 poison res & 100 stun res & always connect hits & hit15","comment":"enable a1/a3 dodge every 15 seconds","real":180.41,"dps":94663,"team":0.2944773191832531,"slices":[["fs",9542],["fs_manachew",21025],["s1_manachew",15610],["s1_manachew_stormlash",2232],["s2_manachew",10111],["s2_manachew_poison",2910],["s3",5631],["s4",8198],["s4_poison",3305],["s4_stormlash",1705],["dx",4748],["ds1_phase2",6901],["dmoon",871],["dfs",1867]],"stats":{"poison":"90.3%","stormlash":"89.0%","team_att_amp":"every 27.52s from 48.93s"}},"IMMUNE-NIHILISM-ANY":{"equip":"IMMUNE-NIHILISM-ANY","adv":"Cecile","ele":"wind","wt":"gun","variant":"DODGE","drg":"Gala_Beast_Volk","wep":"gun-wind-agito","wps":["Memory_of_a_Friend","Sweet_Surprise","The_Lurker_in_the_Woods","Enter_the_Blue_Rose","The_Plaguebringer","Applelicious_Dreams","Testament_of_Eternity"],"coabs":["Gala_Notte","Mona","Yukata_Lathna"],"share":["Grimnir","Formal_Joachim"],"cond":"Curse of Nihility & 999 all affliction res & always connect hits & hit15","comment":"enable a1/a3 dodge every 15 seconds","real":180.41,"dps":47760,"team":0.2944773191832531,"slices":[["fs",5766],["fs_manachew",12142],["s1_manachew",8678],["s1_manachew_stormlash",0],["s2_manachew",5722],["s2_manachew_poison",0],["s3",3128],["s4",4554],["s4_poison",0],["s4_stormlash",0],["dx",2412],["ds1_phase2",3834],["dmoon",484],["dfs",1037]],"stats":{"team_att_amp":"every 27.52s from 48.93s"}},"IMMUNE-NIHILISM-MONO":{"equip":"IMMUNE-NIHILISM-ANY","adv":"Cecile","ele":"wind","wt":"gun","variant":"DODGE","drg":"Gala_Beast_Volk","wep":"gun-wind-agito","wps":["Memory_of_a_Friend","Sweet_Surprise","The_Lurker_in_the_Woods","Enter_the_Blue_Rose","The_Plaguebringer","Applelicious_Dreams","Testament_of_Eternity"],"coabs":["Gala_Notte","Mona","Yukata_Lathna"],"share":["Grimnir","Formal_Joachim"],"cond":"Curse of Nihility & 999 all affliction res & always connect hits & hit15","comment":"enable a1/a3 dodge every 15 seconds","real":180.41,"dps":47760,"team":0.2944773191832531,"slices":[["fs",5766],["fs_manachew",12142],["s1_manachew",8678],["s1_manachew_stormlash",0],["s2_manachew",5722],["s2_manachew_poison",0],["s3",3128],["s4",4554],["s4_poison",0],["s4_stormlash",0],["dx",2412],["ds1_phase2",3834],["dmoon",484],["dfs",1037]],"stats":{"team_att_amp":"every 27.52s from 48.93s"}}}