{"SELF-NORMAL-ANY":{"equip":"SELF-NORMAL-ANY","adv":"The_Prince","ele":"flame","wt":"sword","drg":"Gala_Mars","wep":"sword-flame-agito","wps":["An_Ancient_Oath","Me_and_My_Bestie","The_Red_Impulse","Dueling_Dancers","The_Plaguebringer","Applelicious_Dreams","Testament_of_Eternity"],"coabs":["Halloween_Mym","Kimono_Elisanne","Yuya"],"share":["Weapon","Formal_Joachim"],"cond":"0 burn res & 0 stormlash res & 0 poison res & always connect hits & hp50 & hit15","comment":"","real":180.04,"dps":102062,"team":0.020463543460637303,"slices":[["x",8302],["fs",1502],["s1",22024],["s1_burn",2232],["s2",8328],["s4",5449],["s4_poison",2195],["s4_stormlash",1082],["dx",32502],["ds1",18441]],"stats":{"poison":"72.6%","burn":"68.3%","stormlash":"58.3%"}},"SELF-NORMAL-MONO":{"equip":"SELF-NORMAL-ANY","adv":"The_Prince","ele":"flame","wt":"sword","drg":"Gala_Mars","wep":"sword-flame-agito","wps":["An_Ancient_Oath","Me_and_My_Bestie","The_Red_Impulse","Dueling_Dancers","The_Plaguebringer","Applelicious_Dreams","Testament_of_Eternity"],"coabs":["Halloween_Mym","Kimono_Elisanne","Yuya"],"share":["Weapon","Formal_Joachim"],"cond":"0 burn res & 0 stormlash res & 0 poison res & always connect hits & hp50 & hit15","comment":"","real":180.04,"dps":102062,"team":0.020463543460637303,"slices":[["x",8302],["fs",1502],["s1",22024],["s1_burn",2232],["s2",8328],["s4",5449],["s4_poison",2195],["s4_stormlash",1082],["dx",32502],["ds1",18441]],"stats":{"poison":"72.6%","burn":"68.3%","stormlash":"58.3%"}},"ALWAYS-NORMAL-ANY":{"equip":"ALWAYS-NORMAL-ANY","adv":"The_Prince","ele":"flame","wt":"sword","drg":"Gala_Reborn_Agni","wep":"sword-flame-agito","wps":["An_Ancient_Oath","Me_and_My_Bestie","The_Cutie_Competition","Dueling_Dancers","The_Plaguebringer","Applelicious_Dreams","Testament_of_Eternity"],"coabs":["Halloween_Mym","Kimono_Elisanne","Yuya"],"share":["Weapon","Formal_Joachim"],"cond":"0 burn res & 0 stormlash res & 0 poison res & 0 scorchrend res & always connect hits & hit15","comment":"","real":180.09,"dps":115671,"team":0.02045707356360733,"slices":[["x",10227],["fs",1877],["s1",19441],["s1_burn",2328],["s2",7871],["s4",4284],["s4_poison",1447],["s4_stormlash",772],["dx",35217],["ds1_scorchrend",2907],["ds1",29296]],"stats":{"poison":"58.5%","burn":"100.0%","stormlash":"43.5%","scorchrend":"100.0%"}},"ALWAYS-NORMAL-MONO":{"equip":"ALWAYS-NORMAL-ANY","adv":"The_Prince","ele":"flame","wt":"sword","drg":"Gala_Reborn_Agni","wep":"sword-flame-agito","wps":["An_Ancient_Oath","Me_and_My_Bestie","The_Cutie_Competition","Dueling_Dancers","The_Plaguebringer","Applelicious_Dreams","Testament_of_Eternity"],"coabs":["Halloween_Mym","Kimono_Elisanne","Yuya"],"share":["Weapon","Formal_Joachim"],"cond":"0 burn res & 0 stormlash res & 0 poison res & 0 scorchrend res & always connect hits & hit15","comment":"","real":180.09,"dps":115671,"team":0.02045707356360733,"slices":[["x",10227],["fs",1877],["s1",19441],["s1_burn",2328],["s2",7871],["s4",4284],["s4_poison",1447],["s4_stormlash",772],["dx",35217],["ds1_scorchrend",2907],["ds1",29296]],"stats":{"poison":"58.5%","burn":"100.0%","stormlash":"43.5%","scorchrend":"100.0%"}},"IMMUNE-NORMAL-ANY":{"equip":"IMMUNE-NORMAL-ANY","adv":"The_Prince","ele":"flame","wt":"sword","drg":"Gala_Mars","wep":"sword-flame-agito","wps":["An_Ancient_Oath","The_Bridal_Dragon","The_Red_Impulse","A_Small_Courage","Dueling_Dancers","Applelicious_Dreams","Mask_of_Determination_Bow"],"coabs":["Halloween_Mym","Kimono_Elisanne","Yuya"],"share":["Weapon","Gala_Mym"],"cond":"999 all affliction res & always connect hits & hp50 & hit15","comment":"","real":180.02,"dps":81567,"team":0.020465325844006402,"slices":[["x",4460],["fs",1944],["s1",15788],["s1_burn",0],["s2",7303],["s4",4650],["dx",31026],["ds1",16393]]},"IMMUNE-NORMAL-MONO":{"equip":"IMMUNE-NORMAL-ANY","adv":"The_Prince","ele":"flame","wt":"sword","drg":"Gala_Mars","wep":"sword-flame-agito","wps":["An_Ancient_Oath","The_Bridal_Dragon","The_Red_Impulse","A_Small_Courage","Dueling_Dancers","Applelicious_Dreams","Mask_of_Determination_Bow"],"coabs":["Halloween_Mym","Kimono_Elisanne","Yuya"],"share":["Weapon","Gala_Mym"],"cond":"999 all affliction res & always connect hits & hp50 & hit15","comment":"","real":180.02,"dps":81567,"team":0.020465325844006402,"slices":[["x",4460],["fs",1944],["s1",15788],["s1_burn",0],["s2",7303],["s4",4650],["dx",31026],["ds1",16393]]},"SELF-NIHILISM-ANY":{"equip":"SELF-NIHILISM-ANY","adv":"The_Prince","ele":"flame","wt":"sword","drg":"Gala_Reborn_Agni","wep":"sword-flame-agito","wps":["Emissaries_of_the_Heavens","Me_and_My_Bestie","The_Cutie_Competition","Dueling_Dancers","Entwined_Flames","Applelicious_Dreams","Testament_of_Eternity"],"coabs":["Blade","Halloween_Mym","Kimono_Elisanne"],"share":["Gala_Mym","Humanoid_Mercury"],"cond":"Curse of Nihility & 60 burn res & 100 frostbite res & 0 scorchrend res & always connect hits & hit15","comment":"","real":180.25,"dps":52607,"team":0.0175193646574376,"slices":[["x",3157],["fs",1473],["s1",7945],["s1_burn",447],["s2",3319],["s3",1182],["s4_teamamp",2658],["s4_teamamp_frostbite",0],["dx",15999],["ds1_scorchrend",1278],["ds1",15144]],"stats":{"burn":"29.8%","scorchrend":"55.7%"}},"SELF-NIHILISM-MONO":{"equip":"SELF-NIHILISM-ANY","adv":"The_Prince","ele":"flame","wt":"sword","drg":"Gala_Reborn_Agni","wep":"sword-flame-agito","wps":["Emissaries_of_the_Heavens","Me_and_My_Bestie","The_Cutie_Competition","Dueling_Dancers","Entwined_Flames","Applelicious_Dreams","Testament_of_Eternity"],"coabs":["Blade","Halloween_Mym","Kimono_Elisanne"],"share":["Gala_Mym","Humanoid_Mercury"],"cond":"Curse of Nihility & 60 burn res & 100 frostbite res & 0 scorchrend res & always connect hits & hit15","comment":"","real":180.25,"dps":52607,"team":0.0175193646574376,"slices":[["x",3157],["fs",1473],["s1",7945],["s1_burn",447],["s2",3319],["s3",1182],["s4_teamamp",2658],["s4_teamamp_frostbite",0],["dx",15999],["ds1_scorchrend",1278],["ds1",15144]],"stats":{"burn":"29.8%","scorchrend":"55.7%"}},"ALWAYS-NIHILISM-ANY":{"equip":"ALWAYS-NIHILISM-ANY","adv":"The_Prince","ele":"flame","wt":"sword","drg":"Gala_Reborn_Agni","wep":"sword-flame-agito","wps":["Emissaries_of_the_Heavens","Me_and_My_Bestie","The_Cutie_Competition","Dueling_Dancers","Entwined_Flames","Applelicious_Dreams","Testament_of_Eternity"],"coabs":["Blade","Halloween_Mym","Yuya"],"share":["Gala_Mym","Humanoid_Mercury"],"cond":"Curse of Nihility & 60 burn res & 100 frostbite res & 0 scorchrend res & hit15","comment":"","real":180.11,"dps":67351,"team":0.017533432127404838,"slices":[["x",8030],["fs",516],["s1",10148],["s1_burn",561],["s2",4049],["s3",1514],["s4_teamamp",3397],["s4_teamamp_frostbite",0],["dx",19095],["ds1_scorchrend",1930],["ds1",18106]],"stats":{"burn":"100.0%","scorchrend":"100.0%"}},"ALWAYS-NIHILISM-MONO":{"equip":"ALWAYS-NIHILISM-ANY","adv":"The_Prince","ele":"flame","wt":"sword","drg":"Gala_Reborn_Agni","wep":"sword-flame-agito","wps":["Emissaries_of_the_Heavens","Me_and_My_Bestie","The_Cutie_Competition","Dueling_Dancers","Entwined_Flames","Applelicious_Dreams","Testament_of_Eternity"],"coabs":["Blade","Halloween_Mym","Yuya"],"share":["Gala_Mym","Humanoid_Mercury"],"cond":"Curse of Nihility & 60 burn res & 100 frostbite res & 0 scorchrend res & hit15","comment":"","real":180.11,"dps":67351,"team":0.017533432127404838,"slices":[["x",8030],["fs",516],["s1",10148],["s1_burn",561],["s2",4049],["s3",1514],["s4_teamamp",3397],["s4_teamamp_frostbite",0],["dx",19095],["ds1_scorchrend",1930],["ds1",18106]],"stats":{"burn":"100.0%","scorchrend":"100.0%"}},"IMMUNE-NIHILISM-ANY":{"equip":"IMMUNE-NIHILISM-ANY","adv":"The_Prince","ele":"flame","wt":"sword","drg":"Gala_Reborn_Agni","wep":"sword-flame-agito","wps":["Emissaries_of_the_Heavens","Moonlight_Party","The_Bridal_Dragon","A_Small_Courage","Dueling_Dancers","Applelicious_Dreams","Mask_of_Determination_Bow"],"coabs":["Blade","Halloween_Mym","Kimono_Elisanne"],"share":["Gala_Mym","Humanoid_Mercury"],"cond":"Curse of Nihility & 999 all affliction res & always connect hits & hit15 & hp70","comment":"","real":180.25,"dps":45279,"team":0.0175193646574376,"slices":[["x",2789],["fs",1311],["s1",6949],["s1_burn",0],["s2",2914],["s3",1097],["s4_teamamp",2384],["s4_teamamp_frostbite",0],["dx",14277],["ds1",13554]]},"IMMUNE-NIHILISM-MONO":{"equip":"IMMUNE-NIHILISM-ANY","adv":"The_Prince","ele":"flame","wt":"sword","drg":"Gala_Reborn_Agni","wep":"sword-flame-agito","wps":["Emissaries_of_the_Heavens","Moonlight_Party","The_Bridal_Dragon","A_Small_Courage","Dueling_Dancers","Applelicious_Dreams","Mask_of_Determination_Bow"],"coabs":["Blade","Halloween_Mym","Kimono_Elisanne"],"share":["Gala_Mym","Humanoid_Mercury"],"cond":"Curse of Nihility & 999 all affliction res & always connect hits & hit15 & hp70","comment":"","real":180.25,"dps":45279,"team":0.0175193646574376,"slices":[["x",2789],["fs",1311],["s1",6949],["s1_burn",0],["s2",2914],["s3",1097],["s4_teamamp",2384],["s4_teamamp_frostbite",0],["dx",14277],["ds1",13554]]}}